HandyToolsPy/DataProcess.py
HandyToolsPy/DirTree.py
HandyToolsPy/Draw.py
HandyToolsPy/Transator.py
HandyToolsPy/__init__.py
HandyToolsPy-0.1.10.dist-info/LICENSE
HandyToolsPy-0.1.10.dist-info/METADATA
HandyToolsPy-0.1.10.dist-info/WHEEL
HandyToolsPy-0.1.10.dist-info/top_level.txt
HandyToolsPy-0.1.10.dist-info/RECORD
