Metadata-Version: 2.1
Name: HandyToolsPy
Version: 0.1.10
Summary: Handypy is a multifunctional Python tool library, which aims to provide developers with a series of convenient practical tools and simplify daily programming tasks.Whether it is processing data, operating file systems, or network requests, Handypy can provide you with efficient and reliable solutions.
Home-page: https://github.com/kimbleex/HandyToolsPy
Author: kimbleex
Author-email: kimbleex@outlook.com
License: MIT
Classifier: License :: OSI Approved :: MIT License
Classifier: Programming Language :: Python
Classifier: Programming Language :: Python :: 3.6
Classifier: Programming Language :: Python :: 3.7
Classifier: Programming Language :: Python :: 3.8
Classifier: Programming Language :: Python :: 3.9
Classifier: Programming Language :: Python :: 3.10
Classifier: Programming Language :: Python :: 3.11
Classifier: Programming Language :: Python :: 3.12
Classifier: Programming Language :: Python :: Implementation :: CPython
Classifier: Programming Language :: Python :: Implementation :: PyPy
Requires-Python: >=3.6.0
License-File: LICENSE
Requires-Dist: pandas
Requires-Dist: translate
Requires-Dist: langdetect
